opuspy.cpython-37m-x86_64-linux-gnu.so
opuspy-0.0.3.dist-info/WHEEL
opuspy-0.0.3.dist-info/METADATA
opuspy-0.0.3.dist-info/top_level.txt
opuspy-0.0.3.dist-info/RECORD
opuspy.libs/libopusfile-62a1766f.so.0.4.5
opuspy.libs/libopus-972c2efe.so.0.8.0
opuspy.libs/libopusenc-9b19958b.so.0.4.2
opuspy.libs/libogg-24eaa32b.so.0.8.0
