Metadata-Version: 2.1
Name: opuspy
Version: 0.0.3
Summary: OPUS wrapper.
Author: Eleven Labs
